ec2_proxy/__init__.py
ec2_proxy/ec2_proxy.py
ec2_proxy-0.1.2.dist-info/LICENSE
ec2_proxy-0.1.2.dist-info/METADATA
ec2_proxy-0.1.2.dist-info/WHEEL
ec2_proxy-0.1.2.dist-info/top_level.txt
ec2_proxy-0.1.2.dist-info/RECORD
