Metadata-Version: 2.1
Name: ec2-proxy
Version: 0.1.2
Summary: This package provides ability to use amazon aws as proxy with everchanging IP.
Home-page: https://github.com/AG4lyf/ec2_proxy
Author: Suraj Bhari
Author-email: surajbhari159@gmail.com
License: Apache Software License 2.0
Keywords: ec2_proxy
Platform: UNKNOWN
Classifier: Development Status :: 5 - Production/Stable
Classifier: Intended Audience :: Information Technology
Classifier: License :: OSI Approved :: Apache Software License
Classifier: Natural Language :: English
Classifier: Programming Language :: Python :: 3
Classifier: Programming Language :: Python :: 3.6
Classifier: Programming Language :: Python :: 3.7
Classifier: Programming Language :: Python :: 3.8
Requires-Python: >=3.6
License-File: LICENSE
